foldable_robotics/__init__.py
foldable_robotics/class_algebra.py
foldable_robotics/dxf.py
foldable_robotics/dynamics_info.py
foldable_robotics/general.py
foldable_robotics/geometry.py
foldable_robotics/gmsh_support.py
foldable_robotics/jupyter_support.py
foldable_robotics/laminate.py
foldable_robotics/layer.py
foldable_robotics/manufacturing.py
foldable_robotics/parts-old.py
foldable_robotics/pdf.py
foldable_robotics/plotter_support.py
foldable_robotics/solidworks_support.py
foldable_robotics/parts/__init__.py
foldable_robotics/parts/castellated_hinge1.py
foldable_robotics/parts/castellated_hinge2.py
foldable_robotics/parts/pill_joint.py
foldable_robotics-0.0.36.dist-info/METADATA
foldable_robotics-0.0.36.dist-info/WHEEL
foldable_robotics-0.0.36.dist-info/top_level.txt
foldable_robotics-0.0.36.dist-info/RECORD
