Metadata-Version: 2.1
Name: foldable_robotics
Version: 0.0.36
Summary: Foldable robotics is a package for designing and analyzing foldable laminate robots
Home-page: https://github.com/danaukes/code_foldable_robotics
Author: Dan Aukes
Author-email: danaukes@danaukes.com
License: MIT
Classifier: Programming Language :: Python
Classifier: Programming Language :: Python :: 3
Requires-Dist: ezdxf
Requires-Dist: idealab-tools
Requires-Dist: matplotlib
Requires-Dist: numpy
Requires-Dist: pypoly2tri
Requires-Dist: shapely
Requires-Dist: pyyaml
